encyclopaedia/__init__.py
encyclopaedia/achentry_ren.py
encyclopaedia/actions_ren.py
encyclopaedia/config.rpy
encyclopaedia/constants_ren.py
encyclopaedia/encentry_ren.py
encyclopaedia/encentry_template_ren.py
encyclopaedia/encyclopaedia_ren.py
encyclopaedia/entry_sorting_ren.py
encyclopaedia/eventemitter_ren.py
encyclopaedia/exceptions_ren.py
encyclopaedia/hyperlink_ren.py
encyclopaedia/labels.rpy
encyclopaedia/screens.rpy
encyclopaedia/text_block_ren.py
encyclopaedia/types_ren.py
encyclopaedia/utils_ren.py
encyclopaedia/version.py
encyclopaedia/book/__init__.py
encyclopaedia/book/actions_ren.py
encyclopaedia/book/book_ren.py
renpy_encyclopaedia-3.6.0.dist-info/METADATA
renpy_encyclopaedia-3.6.0.dist-info/WHEEL
renpy_encyclopaedia-3.6.0.dist-info/licenses/LICENSE.md
renpy_encyclopaedia-3.6.0.dist-info/RECORD
