Metadata-Version: 2.3
Name: renpy-encyclopaedia
Version: 3.6.0
Summary: A Ren'Py plugin to create an Encyclopaedia/Glossary/Bestiary or similar system.
Project-URL: Homepage, https://github.com/jsfehler/renpy-encyclopaedia
Project-URL: Bug Tracker, https://github.com/jsfehler/renpy-encyclopaedia/issues
Author: jsfehler
Classifier: License :: OSI Approved :: MIT License
Classifier: Operating System :: OS Independent
Classifier: Programming Language :: Python :: 3
Requires-Python: >=3.9
